{"autoplayBgm": false, "autoplayBgs": false, "battleback1Name": "", "battleback2Name": "", "bgm": {"name": "", "pan": 0, "pitch": 100, "volume": 90}, "bgs": {"name": "", "pan": 0, "pitch": 100, "volume": 90}, "disableDashing": false, "displayName": "", "encounterList": [], "encounterStep": 30, "height": 22, "note": "<par>46\n<cm:coliziadedzinanevestinec>", "parallaxLoopX": false, "parallaxLoopY": false, "parallaxName": "!dedzinanevestinec", "parallaxShow": true, "parallaxSx": 0, "parallaxSy": 0, "scrollType": 0, "specifyBattleback": false, "tilesetId": 2, "width": 24, "data": [0, 0, 0, 0, 0, 0, 0, 0, 0, 0, 0, 0, 0, 0, 0, 0, 0, 0, 0, 0, 0, 0, 0, 0, 0, 0, 0, 0, 0, 0, 0, 0, 0, 0, 0, 0, 0, 0, 0, 0, 0, 0, 0, 0, 0, 0, 0, 0, 0, 0, 0, 0, 0, 0, 0, 0, 0, 0, 0, 0, 0, 0, 0, 0, 0, 0, 0, 0, 0, 0, 0, 0, 0, 0, 0, 0, 0, 0, 0, 0, 0, 0, 0, 0, 0, 0, 0, 0, 0, 0, 0, 0, 0, 0, 0, 0, 0, 0, 0, 0, 0, 0, 0, 0, 0, 0, 0, 0, 0, 0, 0, 0, 0, 0, 0, 0, 0, 0, 0, 0, 0, 0, 0, 0, 0, 0, 0, 0, 0, 0, 0, 0, 0, 0, 0, 0, 0, 0, 0, 0, 0, 0, 0, 0, 0, 0, 0, 0, 0, 0, 0, 0, 0, 0, 0, 0, 0, 0, 0, 0, 0, 0, 0, 0, 0, 0, 0, 0, 0, 0, 0, 0, 0, 0, 0, 0, 0, 0, 0, 0, 0, 0, 0, 0, 0, 0, 0, 0, 0, 0, 0, 0, 0, 0, 0, 0, 0, 0, 0, 0, 0, 0, 0, 0, 0, 0, 0, 0, 0, 0, 0, 0, 0, 0, 0, 0, 0, 0, 0, 0, 0, 0, 0, 0, 0, 0, 0, 0, 0, 0, 0, 0, 0, 0, 0, 0, 0, 0, 0, 0, 0, 0, 0, 0, 0, 0, 0, 0, 0, 0, 0, 0, 0, 0, 0, 0, 0, 0, 0, 0, 0, 0, 0, 0, 0, 0, 0, 0, 0, 0, 0, 0, 0, 0, 0, 0, 0, 0, 0, 0, 0, 0, 0, 0, 0, 0, 0, 0, 0, 0, 0, 0, 0, 0, 0, 0, 0, 0, 0, 0, 0, 0, 0, 0, 0, 0, 0, 0, 0, 0, 0, 0, 0, 0, 0, 0, 0, 0, 0, 0, 0, 0, 0, 0, 0, 0, 0, 0, 0, 0, 0, 0, 0, 0, 0, 0, 0, 0, 0, 0, 0, 0, 0, 0, 0, 0, 0, 0, 0, 0, 0, 0, 0, 0, 0, 0, 0, 0, 0, 0, 0, 0, 0, 0, 0, 0, 0, 0, 0, 0, 0, 0, 0, 0, 0, 0, 0, 0, 0, 0, 0, 0, 0, 0, 0, 0, 0, 0, 0, 0, 0, 0, 0, 0, 0, 0, 0, 0, 0, 0, 0, 0, 0, 0, 0, 0, 0, 0, 0, 0, 0, 0, 0, 0, 0, 0, 0, 0, 0, 0, 0, 0, 0, 0, 0, 0, 0, 0, 0, 0, 0, 0, 0, 0, 0, 0, 0, 0, 0, 0, 0, 0, 0, 0, 0, 0, 0, 0, 0, 0, 0, 0, 0, 0, 0, 0, 0, 0, 0, 0, 0, 0, 0, 0, 0, 0, 0, 0, 0, 0, 0, 0, 0, 0, 0, 0, 0, 0, 0, 0, 0, 0, 0, 0, 0, 0, 0, 0, 0, 0, 0, 0, 0, 0, 0, 0, 0, 0, 0, 0, 0, 0, 0, 0, 0, 0, 0, 0, 0, 0, 0, 0, 0, 0, 0, 0, 0, 0, 0, 0, 0, 0, 0, 0, 0, 0, 0, 0, 0, 0, 0, 0, 0, 0, 0, 0, 0, 0, 0, 0, 0, 0, 0, 0, 0, 0, 0, 0, 0, 0, 0, 0, 0, 0, 0, 0, 0, 0, 0, 0, 0, 0, 0, 0, 0, 0, 0, 0, 0, 0, 0, 0, 0, 0, 0, 0, 0, 0, 0, 0, 0, 0, 0, 0, 0, 0, 0, 0, 0, 0, 0, 0, 0, 0, 0, 0, 0, 0, 0, 0, 0, 0, 0, 0, 0, 0, 0, 0, 0, 0, 0, 0, 0, 0, 0, 0, 0, 0, 0, 0, 0, 0, 0, 0, 0, 0, 0, 0, 0, 0, 0, 0, 0, 0, 0, 0, 0, 0, 0, 0, 0, 0, 0, 0, 0, 0, 0, 0, 0, 0, 0, 0, 0, 0, 0, 0, 0, 0, 0, 0, 0, 0, 0, 0, 0, 0, 0, 0, 0, 0, 0, 0, 0, 0, 0, 0, 0, 0, 0, 0, 0, 0, 0, 0, 0, 0, 0, 0, 0, 0, 0, 0, 0, 0, 0, 0, 0, 0, 0, 0, 0, 0, 0, 0, 0, 0, 0, 0, 0, 0, 0, 0, 0, 0, 0, 0, 0, 0, 0, 0, 0, 0, 0, 0, 0, 0, 0, 0, 0, 0, 0, 0, 0, 0, 0, 0, 0, 0, 0, 0, 0, 0, 0, 0, 0, 0, 0, 0, 0, 0, 0, 0, 0, 0, 0, 0, 0, 0, 0, 0, 0, 0, 0, 0, 0, 0, 0, 0, 0, 0, 0, 0, 0, 0, 0, 0, 0, 0, 0, 0, 0, 0, 0, 0, 0, 0, 0, 0, 0, 0, 0, 0, 0, 0, 0, 0, 0, 0, 0, 0, 0, 0, 0, 0, 0, 0, 0, 0, 0, 0, 0, 0, 0, 0, 0, 0, 0, 0, 0, 0, 0, 0, 0, 0, 0, 0, 0, 0, 0, 0, 0, 0, 0, 0, 0, 0, 0, 0, 0, 0, 0, 0, 0, 0, 0, 0, 0, 0, 0, 0, 0, 0, 0, 0, 0, 0, 0, 0, 0, 0, 0, 0, 0, 0, 0, 0, 0, 0, 0, 0, 0, 0, 0, 0, 0, 0, 0, 0, 0, 0, 0, 0, 0, 0, 0, 0, 0, 0, 0, 0, 0, 0, 0, 0, 0, 0, 0, 0, 0, 0, 0, 0, 0, 0, 0, 0, 0, 0, 0, 0, 0, 0, 0, 0, 0, 0, 0, 0, 0, 0, 0, 0, 0, 0, 0, 0, 0, 0, 0, 0, 0, 0, 0, 0, 0, 0, 0, 0, 0, 0, 0, 0, 0, 0, 0, 0, 0, 0, 0, 0, 0, 0, 0, 0, 0, 0, 0, 0, 0, 0, 0, 0, 0, 0, 0, 0, 0, 0, 0, 0, 0, 0, 0, 0, 0, 0, 0, 0, 0, 0, 0, 0, 0, 0, 0, 0, 0, 0, 0, 0, 0, 0, 0, 0, 0, 0, 0, 0, 0, 0, 0, 0, 0, 0, 0, 0, 0, 0, 0, 0, 0, 0, 0, 0, 0, 0, 0, 0, 0, 0, 0, 0, 0, 0, 0, 0, 0, 0, 0, 0, 0, 0, 0, 0, 0, 0, 0, 0, 0, 0, 0, 0, 0, 0, 0, 0, 0, 0, 0, 0, 0, 0, 0, 0, 0, 0, 0, 0, 0, 0, 0, 0, 0, 0, 0, 0, 0, 0, 0, 0, 0, 0, 0, 0, 0, 0, 0, 0, 0, 0, 0, 0, 0, 0, 0, 0, 0, 0, 0, 0, 0, 0, 0, 0, 0, 0, 0, 0, 0, 0, 0, 0, 0, 0, 0, 0, 0, 0, 0, 0, 0, 0, 0, 0, 0, 0, 0, 0, 0, 0, 0, 0, 0, 0, 0, 0, 0, 0, 0, 0, 0, 0, 0, 0, 0, 0, 0, 0, 0, 0, 0, 0, 0, 0, 0, 0, 0, 0, 0, 0, 0, 0, 0, 0, 0, 0, 0, 0, 0, 0, 0, 0, 0, 0, 0, 0, 0, 0, 0, 0, 0, 0, 0, 0, 0, 0, 0, 0, 0, 0, 0, 0, 0, 0, 0, 0, 0, 0, 0, 0, 0, 0, 0, 0, 0, 0, 0, 0, 0, 0, 0, 0, 0, 0, 0, 0, 0, 0, 0, 0, 0, 0, 0, 0, 0, 0, 0, 0, 0, 0, 0, 0, 0, 0, 0, 0, 0, 0, 0, 0, 0, 0, 0, 0, 0, 0, 0, 0, 0, 0, 0, 0, 0, 0, 0, 0, 0, 0, 0, 0, 0, 0, 0, 0, 0, 0, 0, 0, 0, 0, 0, 0, 0, 0, 0, 0, 0, 0, 0, 0, 0, 0, 0, 0, 0, 0, 0, 0, 0, 0, 0, 0, 0, 0, 0, 0, 0, 0, 0, 0, 0, 0, 0, 0, 0, 0, 0, 0, 0, 0, 0, 0, 0, 0, 0, 0, 0, 0, 0, 0, 0, 0, 0, 0, 0, 0, 0, 0, 0, 0, 0, 0, 0, 0, 0, 0, 0, 0, 0, 0, 0, 0, 0, 0, 0, 0, 0, 0, 0, 0, 0, 0, 0, 0, 0, 0, 0, 0, 0, 0, 0, 0, 0, 0, 0, 0, 0, 0, 0, 0, 0, 0, 0, 0, 0, 0, 0, 0, 0, 0, 0, 0, 0, 0, 0, 0, 0, 0, 0, 0, 0, 0, 0, 0, 0, 0, 0, 0, 0, 0, 0, 0, 0, 0, 0, 0, 0, 0, 0, 0, 0, 0, 0, 0, 0, 0, 0, 0, 0, 0, 0, 0, 0, 0, 0, 0, 0, 0, 0, 0, 0, 0, 0, 0, 0, 0, 0, 0, 0, 0, 0, 0, 0, 0, 0, 0, 0, 0, 0, 0, 0, 0, 0, 0, 0, 0, 0, 0, 0, 0, 0, 0, 0, 0, 0, 0, 0, 0, 0, 0, 0, 0, 0, 0, 0, 0, 0, 0, 0, 0, 0, 0, 0, 0, 0, 0, 0, 0, 0, 0, 0, 0, 0, 0, 0, 0, 0, 0, 0, 0, 0, 0, 0, 0, 0, 0, 0, 0, 0, 0, 0, 0, 0, 0, 0, 0, 0, 0, 0, 0, 0, 0, 0, 0, 0, 0, 0, 0, 0, 0, 0, 0, 0, 0, 0, 0, 0, 0, 0, 0, 0, 0, 0, 0, 0, 0, 0, 0, 0, 0, 0, 0, 0, 0, 0, 0, 0, 0, 0, 0, 0, 0, 0, 0, 0, 0, 0, 0, 0, 0, 0, 0, 0, 0, 0, 0, 0, 0, 0, 0, 0, 0, 0, 0, 0, 0, 0, 0, 0, 0, 0, 0, 0, 0, 0, 0, 0, 0, 0, 0, 0, 0, 0, 0, 0, 0, 0, 0, 0, 0, 0, 0, 0, 0, 0, 0, 0, 0, 0, 0, 0, 0, 0, 0, 0, 0, 0, 0, 0, 0, 0, 0, 0, 0, 0, 0, 0, 0, 0, 0, 0, 0, 0, 0, 0, 0, 0, 0, 0, 0, 0, 0, 0, 0, 0, 0, 0, 0, 0, 0, 0, 0, 0, 0, 0, 0, 0, 0, 0, 0, 0, 0, 0, 0, 0, 0, 0, 0, 0, 0, 0, 0, 0, 0, 0, 0, 0, 0, 0, 0, 0, 0, 0, 0, 0, 0, 0, 0, 0, 0, 0, 0, 0, 0, 0, 0, 0, 0, 0, 0, 0, 0, 0, 0, 0, 0, 0, 0, 0, 0, 0, 0, 0, 0, 0, 0, 0, 0, 0, 0, 0, 0, 0, 0, 0, 0, 0, 0, 0, 0, 0, 0, 0, 0, 0, 0, 0, 0, 0, 0, 0, 0, 0, 0, 0, 0, 0, 0, 0, 0, 0, 0, 0, 0, 0, 0, 0, 0, 0, 0, 0, 0, 0, 0, 0, 0, 0, 0, 0, 0, 0, 0, 0, 0, 0, 0, 0, 0, 0, 0, 0, 0, 0, 0, 0, 0, 0, 0, 0, 0, 0, 0, 0, 0, 0, 0, 0, 0, 0, 0, 0, 0, 0, 0, 0, 0, 0, 0, 0, 0, 0, 0, 0, 0, 0, 0, 0, 0, 0, 0, 0, 0, 0, 0, 0, 0, 0, 0, 0, 0, 0, 0, 0, 0, 0, 0, 0, 0, 0, 0, 0, 0, 0, 0, 0, 0, 0, 0, 0, 0, 0, 0, 0, 0, 0, 0, 0, 0, 0, 0, 0, 0, 0, 0, 0, 0, 0, 0, 0, 0, 0, 0, 0, 0, 0, 0, 0, 0, 0, 0, 0, 0, 0, 0, 0, 0, 0, 0, 0, 0, 0, 0, 0, 0, 0, 0, 0, 0, 0, 0, 0, 0, 0, 0, 0, 0, 0, 0, 0, 0, 0, 0, 0, 0, 0, 0, 0, 0, 0, 0, 0, 0, 0, 0, 0, 0, 0, 0, 0, 0, 0, 0, 0, 0, 0, 0, 0, 0, 0, 0, 0, 0, 0, 0, 0, 0, 0, 0, 0, 0, 0, 0, 0, 0, 0, 0, 0, 0, 0, 0, 0, 0, 0, 0, 0, 0, 0, 0, 0, 0, 0, 0, 0, 0, 0, 0, 0, 0, 0, 0, 0, 0, 0, 0, 0, 0, 0, 0, 0, 0, 0, 0, 0, 0, 0, 0, 0, 0, 0, 0, 0, 0, 0, 0, 0, 0, 0, 0, 0, 0, 0, 0, 0, 0, 0, 0, 0, 0, 0, 0, 0, 0, 0, 0, 0, 0, 0, 0, 0, 0, 0, 0, 0, 0, 0, 0, 0, 0, 0, 0, 0, 0, 0, 0, 0, 0, 0, 0, 0, 0, 0, 0, 0, 0, 0, 0, 0, 0, 0, 0, 0, 0, 0, 0, 0, 0, 0, 0, 0, 0, 0, 0, 0, 0, 0, 0, 0, 0, 0, 0, 0, 0, 0, 0, 0, 0, 0, 0, 0, 0, 0, 0, 0, 0, 0, 0, 0, 0, 0, 0, 0, 0, 0, 0, 0, 0, 0, 0, 0, 0, 0, 0, 0, 0, 0, 0, 0, 0, 0, 0, 0, 0, 0, 0, 0, 0, 0, 0, 0, 0, 0, 0, 0, 0, 0, 0, 0, 0, 0, 0, 0, 0, 0, 0, 0, 0, 0, 0, 0, 0, 0, 0, 0, 0, 0, 0, 0, 0, 0, 0, 0, 0, 0, 0, 0, 0, 0, 0, 0, 0, 0, 0, 0, 0, 0, 0, 0, 0, 0, 0, 0, 0, 0, 0, 0, 0, 0, 0, 0, 0, 0, 0, 0, 0, 0, 0, 0, 0, 0, 0, 0, 0, 0, 0, 0, 0, 0, 0, 0, 0, 0, 0, 0, 0, 0, 0, 0, 0, 0, 0, 0, 0, 0, 0, 0, 0, 0, 0, 0, 0, 0, 0, 0, 0, 0, 0, 0, 0, 0, 0, 0, 0, 0, 0, 0, 0, 0, 0, 0, 0, 0, 0, 0, 0, 0, 0, 0, 0, 0, 0, 0, 0, 0, 0, 0, 0, 0, 0, 0, 0, 0, 0, 0, 0, 0, 0, 0, 0, 0, 0, 0, 0, 0, 0, 0, 0, 0, 0, 0, 0, 0, 0, 0, 0, 0, 0, 0, 0, 0, 0, 0, 0, 0, 0, 0, 0, 0, 0, 0, 0, 0, 0, 0, 0, 0, 0, 0, 0, 0, 0, 0, 0, 0, 0, 0, 0, 0, 0, 0, 0, 0, 0, 0, 0, 0, 0, 0, 0, 0, 0, 0, 0, 0, 0, 0, 0, 0, 0, 0, 0, 0, 0, 0, 0, 0, 0, 0, 0, 0, 0, 0, 0, 0, 0, 0, 0, 0, 0, 0, 0, 0, 0, 0, 0, 0, 0, 0, 0, 0, 0, 0, 0, 0, 0, 0, 0, 0, 0, 0, 0, 0, 0, 0, 0, 0, 0, 0, 0, 0, 0, 0, 0, 0, 0, 0, 0, 0, 0, 0, 0, 0, 0, 0, 0, 0, 0, 0, 0, 0, 0, 0, 0, 0, 0, 0, 0, 0, 0, 0, 0, 0, 0, 0, 0, 0, 0, 0, 0, 0, 0, 0, 0, 0, 0, 0, 0, 0, 0, 0, 0, 0, 0, 0, 0, 0, 0, 0, 0, 0, 0, 0, 0, 0, 0, 0, 0, 0, 0, 0, 0, 0, 0, 0, 0, 0, 0, 0, 0, 0, 0, 0, 0, 0, 0, 0, 0, 0, 0, 0, 0, 0, 0, 0, 0, 0, 0, 0, 0, 0, 0, 0, 0, 0, 0, 0, 0, 0, 0, 0, 0, 0, 0, 0, 0, 0, 0, 0, 0, 0, 0, 0, 0, 0, 0, 0, 0, 0, 0, 0, 0, 0, 0, 0, 0, 0, 0, 0, 0, 0, 0, 0, 0, 0, 0, 0, 0, 0, 0, 0, 0, 0, 0, 0, 0, 0, 0, 0, 0, 0, 0, 0, 0, 0, 0, 0, 0, 0, 0, 0, 0, 0, 0, 0, 0, 0, 0, 0, 0, 0, 0, 0, 0, 0, 0, 0, 0, 0, 0, 0, 0, 0, 0, 0, 0, 0, 0, 0, 0, 0, 0, 0, 0, 0, 0, 0, 0, 0, 0, 0, 0, 0, 0, 0, 0, 0, 0, 0, 0, 0, 0, 0, 0, 0, 0, 0, 0, 0, 0, 0, 0, 0, 0, 0, 0, 0, 0, 0, 0, 0, 0, 0, 0, 0, 0, 0, 0, 0, 0, 0, 0, 0, 0, 0, 0, 0, 0, 0, 0, 0, 0, 0, 0, 0, 0, 0, 0, 0, 0, 0, 0, 0, 0, 0, 0, 0, 0, 0, 0, 0, 0, 0, 0, 0, 0, 0, 0, 0, 0, 0, 0, 0, 0, 0, 0, 0, 0, 0, 0, 0, 0, 0, 0, 0, 0, 0, 0, 0, 0, 0, 0, 0, 0, 0, 0, 0, 0, 0, 0, 0, 0, 0, 0, 0, 0, 0, 0, 0, 0, 0, 0, 0, 0, 0, 0, 0, 0, 0, 0, 0, 0, 0, 0, 0, 0, 0, 0, 0, 0, 0, 0, 0, 0, 0, 0, 0, 0, 0, 0, 0, 0, 0, 0, 0, 0, 0, 0, 0, 0, 0, 0, 0, 0, 0, 0, 0, 0, 0, 0, 0, 0, 0, 0, 0, 0, 0, 0, 0, 0, 0, 0, 0, 0, 0, 0, 0, 2, 2, 2, 2, 2, 0, 0, 0, 0, 0, 0, 0, 0, 0, 0, 0, 0, 0, 0, 0, 0, 0, 0, 2, 2, 2, 2, 2, 2, 0, 0, 0, 0, 0, 0, 0, 0, 0, 0, 0, 0, 0, 0, 0, 0, 0, 0, 2, 2, 2, 2, 2, 2, 2, 0, 0, 0, 0, 0, 0, 0, 0, 0, 0, 0, 0, 0, 0, 0, 0, 2, 2, 2, 4, 4, 4, 4, 2, 0, 0, 0, 0, 0, 0, 0, 0, 0, 0, 0, 0, 0, 0, 0, 4, 4, 2, 4, 4, 4, 4, 4, 2, 2, 0, 0, 0, 0, 0, 0, 0, 0, 0, 4, 4, 4, 4, 4, 4, 4, 4, 4, 4, 4, 4, 4, 2, 2, 0, 0, 0, 0, 0, 0, 0, 0, 0, 4, 4, 4, 4, 4, 4, 4, 4, 4, 4, 2, 2, 2, 2, 2, 0, 0, 0, 0, 0, 0, 0, 0, 0, 4, 4, 4, 4, 4, 4, 4, 4, 0, 2, 2, 2, 2, 2, 2, 2, 0, 0, 0, 0, 0, 0, 0, 0, 4, 4, 4, 4, 4, 4, 4, 0, 0, 2, 2, 2, 2, 2, 2, 0, 0, 0, 0, 0, 0, 0, 0, 0, 0, 0, 0, 0, 0, 0, 0, 0, 0, 0, 0, 0, 0, 0, 0, 0, 0, 0, 0, 0, 0, 0, 0, 0, 0, 0, 0, 0, 0, 0, 0, 0, 0, 0, 0, 0, 0, 0, 0, 0, 0, 0, 0, 0, 0, 0, 0, 0, 0, 0, 0, 0, 0, 0, 0, 0, 0, 0, 0, 0, 0, 0, 0, 0, 0, 0, 0, 0, 0, 0, 0, 0, 0, 0, 0, 0, 0, 0, 0, 0, 0, 0, 0, 0, 0, 0, 0, 0, 0, 0, 0, 0, 0, 0, 0, 0, 0, 0, 0, 0, 0, 0, 0, 0, 0, 0, 0, 0, 0, 0, 0, 0, 0, 0, 0, 0, 0, 0, 0, 0, 0, 0, 0, 0, 0, 0, 0, 0, 0, 0, 0, 0, 0, 0, 0, 0, 0, 0, 0, 0, 0, 0, 0, 0, 0, 0, 0, 0, 0, 0, 0, 0, 0, 0, 0, 0, 0, 0, 0, 0, 0, 0, 0, 0, 0], "events": [null, {"id": 1, "name": "EV001", "note": "", "pages": [{"conditions": {"actorId": 1, "actorValid": false, "itemId": 1, "itemValid": false, "selfSwitchCh": "A", "selfSwitchValid": false, "switch1Id": 1, "switch1Valid": false, "switch2Id": 1, "switch2Valid": false, "variableId": 1, "variableValid": false, "variableValue": 0}, "directionFix": false, "image": {"tileId": 0, "characterName": "QVLADO-vlado", "direction": 2, "pattern": 0, "characterIndex": 0}, "list": [{"code": 0, "indent": 0, "parameters": []}], "moveFrequency": 3, "moveRoute": {"list": [{"code": 0, "parameters": []}], "repeat": true, "skippable": false, "wait": false}, "moveSpeed": 3, "moveType": 0, "priorityType": 1, "stepAnime": false, "through": false, "trigger": 0, "walkAnime": true}, {"conditions": {"actorId": 1, "actorValid": false, "itemId": 1, "itemValid": false, "selfSwitchCh": "A", "selfSwitchValid": false, "switch1Id": 1, "switch1Valid": false, "switch2Id": 1, "switch2Valid": false, "variableId": 11, "variableValid": true, "variableValue": 2}, "directionFix": false, "image": {"characterIndex": 0, "characterName": "", "direction": 2, "pattern": 0, "tileId": 0}, "list": [{"code": 0, "indent": 0, "parameters": []}], "moveFrequency": 3, "moveRoute": {"list": [{"code": 0, "parameters": []}], "repeat": true, "skippable": false, "wait": false}, "moveSpeed": 3, "moveType": 0, "priorityType": 0, "stepAnime": false, "through": false, "trigger": 0, "walkAnime": true}, {"conditions": {"actorId": 1, "actorValid": false, "itemId": 1, "itemValid": false, "selfSwitchCh": "A", "selfSwitchValid": false, "switch1Id": 1, "switch1Valid": false, "switch2Id": 1, "switch2Valid": false, "variableId": 23, "variableValid": true, "variableValue": 7}, "directionFix": false, "image": {"tileId": 0, "characterName": "QVLADO-vlado", "direction": 2, "pattern": 0, "characterIndex": 0}, "list": [{"code": 231, "indent": 0, "parameters": [1, "bohatier vlado", 1, 0, 240, 550, 100, 100, 255, 0]}, {"code": 101, "indent": 0, "parameters": ["", 0, 0, 2]}, {"code": 401, "indent": 0, "parameters": ["Уж вы-то поговорили?"]}, {"code": 401, "indent": 0, "parameters": ["\\n<Пип Владо>"]}, {"code": 235, "indent": 0, "parameters": [1]}, {"code": 0, "indent": 0, "parameters": []}], "moveFrequency": 3, "moveRoute": {"list": [{"code": 0, "parameters": []}], "repeat": true, "skippable": false, "wait": false}, "moveSpeed": 3, "moveType": 0, "priorityType": 1, "stepAnime": false, "through": false, "trigger": 0, "walkAnime": true}, {"conditions": {"actorId": 1, "actorValid": false, "itemId": 1, "itemValid": false, "selfSwitchCh": "A", "selfSwitchValid": false, "switch1Id": 1, "switch1Valid": false, "switch2Id": 1, "switch2Valid": false, "variableId": 23, "variableValid": true, "variableValue": 9}, "directionFix": false, "image": {"tileId": 0, "characterName": "QVLADO-vlado", "direction": 2, "pattern": 0, "characterIndex": 0}, "list": [{"code": 231, "indent": 0, "parameters": [1, "bohatier vlado", 1, 0, 240, 550, 100, 100, 255, 0]}, {"code": 101, "indent": 0, "parameters": ["", 0, 0, 2]}, {"code": 401, "indent": 0, "parameters": ["Хлопи, уж не в музыке дело, а с кем-то, кого ты любишь. Ты,"]}, {"code": 401, "indent": 0, "parameters": ["мейс леквар и Ореховичу. \\n<Пип Владо>"]}, {"code": 235, "indent": 0, "parameters": [1]}, {"code": 101, "indent": 0, "parameters": ["", 0, 0, 2]}, {"code": 401, "indent": 0, "parameters": ["Досталь С.И.[1]Леквар К.[2] А.к.[3]Ореховичу К.[4]."]}, {"code": 126, "indent": 0, "parameters": [21, 0, 0, 1]}, {"code": 126, "indent": 0, "parameters": [9, 0, 0, 1]}, {"code": 123, "indent": 0, "parameters": ["A", 0]}, {"code": 0, "indent": 0, "parameters": []}], "moveFrequency": 3, "moveRoute": {"list": [{"code": 0, "parameters": []}], "repeat": true, "skippable": false, "wait": false}, "moveSpeed": 3, "moveType": 0, "priorityType": 1, "stepAnime": false, "through": false, "trigger": 0, "walkAnime": true}, {"conditions": {"actorId": 1, "actorValid": false, "itemId": 1, "itemValid": false, "selfSwitchCh": "A", "selfSwitchValid": true, "switch1Id": 1, "switch1Valid": false, "switch2Id": 1, "switch2Valid": false, "variableId": 23, "variableValid": false, "variableValue": 9}, "directionFix": false, "image": {"tileId": 0, "characterName": "QVLADO-vlado", "direction": 2, "pattern": 0, "characterIndex": 0}, "list": [{"code": 231, "indent": 0, "parameters": [1, "bohatier vlado", 1, 0, 240, 550, 100, 100, 255, 0]}, {"code": 101, "indent": 0, "parameters": ["", 0, 0, 2]}, {"code": 401, "indent": 0, "parameters": ["Буде света жива."]}, {"code": 401, "indent": 0, "parameters": ["\\n<Пип Владо>"]}, {"code": 235, "indent": 0, "parameters": [1]}, {"code": 0, "indent": 0, "parameters": []}], "moveFrequency": 3, "moveRoute": {"list": [{"code": 0, "parameters": []}], "repeat": true, "skippable": false, "wait": false}, "moveSpeed": 3, "moveType": 0, "priorityType": 1, "stepAnime": false, "through": false, "trigger": 0, "walkAnime": true}, {"conditions": {"actorId": 1, "actorValid": false, "itemId": 1, "itemValid": false, "selfSwitchCh": "A", "selfSwitchValid": false, "switch1Id": 1, "switch1Valid": false, "switch2Id": 1, "switch2Valid": false, "variableId": 25, "variableValid": true, "variableValue": 1}, "directionFix": false, "image": {"characterIndex": 0, "characterName": "", "direction": 2, "pattern": 0, "tileId": 0}, "list": [{"code": 0, "indent": 0, "parameters": []}], "moveFrequency": 3, "moveRoute": {"list": [{"code": 0, "parameters": []}], "repeat": true, "skippable": false, "wait": false}, "moveSpeed": 3, "moveType": 0, "priorityType": 0, "stepAnime": false, "through": false, "trigger": 0, "walkAnime": true}], "x": 9, "y": 10}, {"id": 2, "name": "EV002", "note": "<collider: Circle, 36, 24, 12, 24>", "pages": [{"conditions": {"actorId": 1, "actorValid": false, "itemId": 1, "itemValid": false, "selfSwitchCh": "A", "selfSwitchValid": false, "switch1Id": 1, "switch1Valid": false, "switch2Id": 1, "switch2Valid": false, "variableId": 1, "variableValid": false, "variableValue": 0}, "directionFix": false, "image": {"tileId": 0, "characterName": "QNEVIESTKA-neviestka", "direction": 2, "pattern": 0, "characterIndex": 0}, "list": [{"code": 231, "indent": 0, "parameters": [1, "hrdina palo", 1, 0, 720, 540, 100, 100, 255, 0]}, {"code": 101, "indent": 0, "parameters": ["", 0, 0, 2]}, {"code": 401, "indent": 0, "parameters": ["Нужен.\\к[1]<Павел>"]}, {"code": 235, "indent": 0, "parameters": [1]}, {"code": 231, "indent": 0, "parameters": [1, "NPC neviestka", 1, 0, 240, 520, 100, 100, 255, 0]}, {"code": 101, "indent": 0, "parameters": ["", 0, 0, 2]}, {"code": 401, "indent": 0, "parameters": ["Живите, друзья. Кто-нибудь, с кем вы могли бы"]}, {"code": 401, "indent": 0, "parameters": ["справиться?\\к[1]<Неизвестка>"]}, {"code": 235, "indent": 0, "parameters": [1]}, {"code": 231, "indent": 0, "parameters": [1, "hrdina matej", 1, 0, 240, 520, 100, 100, 255, 0]}, {"code": 101, "indent": 0, "parameters": ["", 0, 0, 2]}, {"code": 401, "indent": 0, "parameters": ["Найвиак нам поможет, ак нам порадует, кам мохол Исмаил"]}, {"code": 401, "indent": 0, "parameters": ["фарар.\\n<Матей>"]}, {"code": 235, "indent": 0, "parameters": [1]}, {"code": 231, "indent": 0, "parameters": [1, "NPC neviestka", 1, 0, 240, 520, 100, 100, 255, 0]}, {"code": 101, "indent": 0, "parameters": ["", 0, 0, 2]}, {"code": 401, "indent": 0, "parameters": ["<Перенос слов>так, чтобы môžem ľahko. Vždy по naších stretnutiach chodí делать"]}, {"code": 401, "indent": 0, "parameters": ["kostola. Pripravuje kázeň вашему Ан. Не хотите ли порадоваться, что я"]}, {"code": 401, "indent": 0, "parameters": ["вам помог? Кто-то мог, кто-то на тебя, ритьеру? \\n<Неизвестка>"]}, {"code": 102, "indent": 0, "parameters": [["Добрый день.", "Нието Часу."], 1, 0, 2, 0]}, {"code": 402, "indent": 0, "parameters": [0, "Добрый день."]}, {"code": 235, "indent": 1, "parameters": [1]}, {"code": 231, "indent": 1, "parameters": [1, "hrdina palo", 1, 0, 720, 540, 100, 100, 255, 0]}, {"code": 101, "indent": 1, "parameters": ["", 0, 0, 2]}, {"code": 401, "indent": 1, "parameters": ["С кем это ты? Патрило, раз за разом меняющий"]}, {"code": 401, "indent": 1, "parameters": ["сознание.\\n<Павел>"]}, {"code": 235, "indent": 1, "parameters": [1]}, {"code": 231, "indent": 1, "parameters": [1, "hrdina matej", 1, 0, 240, 520, 100, 100, 255, 0]}, {"code": 101, "indent": 1, "parameters": ["", 0, 0, 2]}, {"code": 401, "indent": 1, "parameters": ["Я надеюсь, что все это останется в тайне.\\к[1]<Матей>"]}, {"code": 235, "indent": 1, "parameters": [1]}, {"code": 221, "indent": 1, "parameters": []}, {"code": 230, "indent": 1, "parameters": [30]}, {"code": 121, "indent": 1, "parameters": [44, 44, 0]}, {"code": 222, "indent": 1, "parameters": []}, {"code": 231, "indent": 1, "parameters": [1, "hrdina palo holoprd", 1, 0, 720, 540, 100, 100, 255, 0]}, {"code": 101, "indent": 1, "parameters": ["", 0, 0, 2]}, {"code": 401, "indent": 1, "parameters": ["Я добр. Навоняны с яком сэмом папежем.\\к[1]<Павел>"]}, {"code": 235, "indent": 1, "parameters": [1]}, {"code": 231, "indent": 1, "parameters": [1, "NPC neviestka", 1, 0, 240, 520, 100, 100, 255, 0]}, {"code": 101, "indent": 1, "parameters": ["", 0, 0, 2]}, {"code": 401, "indent": 1, "parameters": ["Я хочу, чтобы ты был рядом. Если ты рядом.\\к[1]<Неизвестка>"]}, {"code": 235, "indent": 1, "parameters": [1]}, {"code": 0, "indent": 1, "parameters": []}, {"code": 402, "indent": 0, "parameters": [1, "Нието Часу."]}, {"code": 235, "indent": 1, "parameters": [1]}, {"code": 0, "indent": 1, "parameters": []}, {"code": 404, "indent": 0, "parameters": []}, {"code": 0, "indent": 0, "parameters": []}], "moveFrequency": 3, "moveRoute": {"list": [{"code": 0, "parameters": []}], "repeat": true, "skippable": false, "wait": false}, "moveSpeed": 3, "moveType": 0, "priorityType": 1, "stepAnime": false, "through": false, "trigger": 0, "walkAnime": true}, {"conditions": {"actorId": 1, "actorValid": false, "itemId": 1, "itemValid": false, "selfSwitchCh": "A", "selfSwitchValid": false, "switch1Id": 1, "switch1Valid": false, "switch2Id": 1, "switch2Valid": false, "variableId": 23, "variableValid": true, "variableValue": 6}, "directionFix": false, "image": {"tileId": 0, "characterName": "QNEVIESTKA-neviestka", "direction": 2, "pattern": 0, "characterIndex": 0}, "list": [{"code": 231, "indent": 0, "parameters": [1, "NPC neviestka", 1, 0, 240, 520, 100, 100, 255, 0]}, {"code": 117, "indent": 0, "parameters": [33]}, {"code": 0, "indent": 0, "parameters": []}], "moveFrequency": 3, "moveRoute": {"list": [{"code": 0, "parameters": []}], "repeat": true, "skippable": false, "wait": false}, "moveSpeed": 3, "moveType": 0, "priorityType": 1, "stepAnime": false, "through": false, "trigger": 0, "walkAnime": true}, {"conditions": {"actorId": 1, "actorValid": false, "itemId": 1, "itemValid": false, "selfSwitchCh": "A", "selfSwitchValid": false, "switch1Id": 1, "switch1Valid": false, "switch2Id": 1, "switch2Valid": false, "variableId": 23, "variableValid": true, "variableValue": 7}, "directionFix": false, "image": {"tileId": 0, "characterName": "QNEVIESTKA-neviestka", "direction": 2, "pattern": 0, "characterIndex": 0}, "list": [{"code": 231, "indent": 0, "parameters": [1, "NPC neviestka", 1, 0, 240, 520, 100, 100, 255, 0]}, {"code": 101, "indent": 0, "parameters": ["", 0, 0, 2]}, {"code": 401, "indent": 0, "parameters": ["Я хочу, чтобы ты был неблагодарным, Боже, совсем как"]}, {"code": 401, "indent": 0, "parameters": ["неччела. Мама, которая любит тебя. Уж если болеть не за"]}, {"code": 401, "indent": 0, "parameters": ["что.\\к[1]<Неизвестка>"]}, {"code": 235, "indent": 0, "parameters": [1]}, {"code": 0, "indent": 0, "parameters": []}], "moveFrequency": 3, "moveRoute": {"list": [{"code": 0, "parameters": []}], "repeat": true, "skippable": false, "wait": false}, "moveSpeed": 3, "moveType": 0, "priorityType": 1, "stepAnime": false, "through": false, "trigger": 0, "walkAnime": true}, {"conditions": {"actorId": 1, "actorValid": false, "itemId": 1, "itemValid": false, "selfSwitchCh": "A", "selfSwitchValid": false, "switch1Id": 1, "switch1Valid": false, "switch2Id": 1, "switch2Valid": false, "variableId": 25, "variableValid": true, "variableValue": 1}, "directionFix": false, "image": {"tileId": 0, "characterName": "QKULKEK-kulkek", "direction": 2, "pattern": 0, "characterIndex": 0}, "list": [{"code": 301, "indent": 0, "parameters": [0, 46, false, false]}, {"code": 123, "indent": 0, "parameters": ["A", 0]}, {"code": 0, "indent": 0, "parameters": []}], "moveFrequency": 2, "moveRoute": {"list": [{"code": 2, "indent": null}, {"code": 3, "indent": null}, {"code": 0, "parameters": []}], "repeat": true, "skippable": false, "wait": false}, "moveSpeed": 3, "moveType": 3, "priorityType": 1, "stepAnime": false, "through": false, "trigger": 1, "walkAnime": true}, {"conditions": {"actorId": 1, "actorValid": false, "itemId": 1, "itemValid": false, "selfSwitchCh": "A", "selfSwitchValid": true, "switch1Id": 1, "switch1Valid": false, "switch2Id": 1, "switch2Valid": false, "variableId": 1, "variableValid": false, "variableValue": 0}, "directionFix": false, "image": {"characterIndex": 0, "characterName": "", "direction": 2, "pattern": 0, "tileId": 0}, "list": [{"code": 0, "indent": 0, "parameters": []}], "moveFrequency": 3, "moveRoute": {"list": [{"code": 0, "parameters": []}], "repeat": true, "skippable": false, "wait": false}, "moveSpeed": 3, "moveType": 0, "priorityType": 0, "stepAnime": false, "through": false, "trigger": 0, "walkAnime": true}], "x": 14, "y": 11}, {"id": 3, "name": "EV003", "note": "<collider: Circle, 120, 120, 0, 24>", "pages": [{"conditions": {"actorId": 1, "actorValid": false, "itemId": 1, "itemValid": false, "selfSwitchCh": "A", "selfSwitchValid": false, "switch1Id": 1, "switch1Valid": false, "switch2Id": 1, "switch2Valid": false, "variableId": 1, "variableValid": false, "variableValue": 0}, "directionFix": false, "image": {"characterIndex": 0, "characterName": "", "direction": 2, "pattern": 0, "tileId": 0}, "list": [{"code": 201, "indent": 0, "parameters": [0, 44, 13, 16, 4, 0]}, {"code": 0, "indent": 0, "parameters": []}], "moveFrequency": 3, "moveRoute": {"list": [{"code": 0, "parameters": []}], "repeat": true, "skippable": false, "wait": false}, "moveSpeed": 3, "moveType": 0, "priorityType": 0, "stepAnime": false, "through": false, "trigger": 1, "walkAnime": true}], "x": 3, "y": 12}, {"id": 4, "name": "EV004", "note": "<collider: Circle, 120, 120, 0, 24>", "pages": [{"conditions": {"actorId": 1, "actorValid": false, "itemId": 1, "itemValid": false, "selfSwitchCh": "A", "selfSwitchValid": false, "switch1Id": 1, "switch1Valid": false, "switch2Id": 1, "switch2Valid": false, "variableId": 1, "variableValid": false, "variableValue": 0}, "directionFix": false, "image": {"characterIndex": 0, "characterName": "", "direction": 2, "pattern": 0, "tileId": 0}, "list": [{"code": 201, "indent": 0, "parameters": [0, 44, 21, 18, 4, 0]}, {"code": 0, "indent": 0, "parameters": []}], "moveFrequency": 3, "moveRoute": {"list": [{"code": 0, "parameters": []}], "repeat": true, "skippable": false, "wait": false}, "moveSpeed": 3, "moveType": 0, "priorityType": 0, "stepAnime": false, "through": false, "trigger": 1, "walkAnime": true}], "x": 11, "y": 13}, {"id": 5, "name": "EV005", "note": "<collider: Circle, 36, 24, 12, 24>", "pages": [{"conditions": {"actorId": 1, "actorValid": false, "itemId": 1, "itemValid": false, "selfSwitchCh": "A", "selfSwitchValid": false, "switch1Id": 1, "switch1Valid": false, "switch2Id": 1, "switch2Valid": false, "variableId": 14, "variableValid": false, "variableValue": 1}, "directionFix": false, "image": {"tileId": 0, "characterName": "QNEVIESTKA1-neviestka1", "direction": 2, "pattern": 0, "characterIndex": 0}, "list": [{"code": 231, "indent": 0, "parameters": [1, "NPC devka verzia c", 1, 0, 240, 480, 100, 100, 255, 0]}, {"code": 101, "indent": 0, "parameters": ["", 0, 0, 2]}, {"code": 401, "indent": 0, "parameters": ["Фиха, духовенство и шачта, к которым мы привыкли, значит,"]}, {"code": 401, "indent": 0, "parameters": ["невита. Кто-то из вас мог оказать услугу? Пришли сюда, чтобы"]}, {"code": 401, "indent": 0, "parameters": ["забрать тебя?\"[1]<Неизвестка>"]}, {"code": 235, "indent": 0, "parameters": [1]}, {"code": 231, "indent": 0, "parameters": [1, "hrdina matej", 1, 0, 240, 550, 100, 100, 255, 0]}, {"code": 101, "indent": 0, "parameters": ["", 0, 0, 2]}, {"code": 401, "indent": 0, "parameters": ["На неможе. Моя закуска.\\к[1]<Матей>"]}, {"code": 235, "indent": 0, "parameters": [1]}, {"code": 231, "indent": 0, "parameters": [1, "hrdina palo", 1, 0, 720, 540, 100, 100, 255, 0]}, {"code": 101, "indent": 0, "parameters": ["", 0, 0, 2]}, {"code": 401, "indent": 0, "parameters": ["Масею! Ты не хочешь, чтобы тераз, я хочу, чтобы мама с тобой"]}, {"code": 401, "indent": 0, "parameters": ["рассталась?! \\! Я хочу быть с тобой.\\! Я так хочу быть с мамой"]}, {"code": 401, "indent": 0, "parameters": ["тераз. Пипа хадаме, незнаш, кам мохол, ЗАО?\\к[3]<Павел>"]}, {"code": 235, "indent": 0, "parameters": [1]}, {"code": 231, "indent": 0, "parameters": [1, "NPC devka verzia c", 1, 0, 240, 480, 100, 100, 255, 0]}, {"code": 101, "indent": 0, "parameters": ["", 0, 0, 2]}, {"code": 401, "indent": 0, "parameters": ["Как поступить с костоломом, не так ли?\"[1]<Неизвестка>"]}, {"code": 235, "indent": 0, "parameters": [1]}, {"code": 231, "indent": 0, "parameters": [1, "hrdina palo", 1, 0, 720, 540, 100, 100, 255, 0]}, {"code": 101, "indent": 0, "parameters": ["", 0, 0, 2]}, {"code": 401, "indent": 0, "parameters": ["Привет, от малого и среднего бизнеса Мохли Скушича. А кто"]}, {"code": 401, "indent": 0, "parameters": ["пил?\\к[1]<Павел>"]}, {"code": 235, "indent": 0, "parameters": [1]}, {"code": 231, "indent": 0, "parameters": [1, "NPC devka verzia c", 1, 0, 240, 480, 100, 100, 255, 0]}, {"code": 101, "indent": 0, "parameters": ["", 0, 0, 2]}, {"code": 401, "indent": 0, "parameters": ["Никогда, никогда я не был таким добрым, чтобы чувствовать,"]}, {"code": 401, "indent": 0, "parameters": ["что ты такой милый.\\к[1]<Неизвестка>"]}, {"code": 235, "indent": 0, "parameters": [1]}, {"code": 0, "indent": 0, "parameters": []}], "moveFrequency": 3, "moveRoute": {"list": [{"code": 0, "parameters": []}], "repeat": true, "skippable": false, "wait": false}, "moveSpeed": 3, "moveType": 0, "priorityType": 1, "stepAnime": false, "through": false, "trigger": 0, "walkAnime": true}, {"conditions": {"actorId": 1, "actorValid": false, "itemId": 1, "itemValid": false, "selfSwitchCh": "A", "selfSwitchValid": false, "switch1Id": 1, "switch1Valid": false, "switch2Id": 1, "switch2Valid": false, "variableId": 23, "variableValid": true, "variableValue": 6}, "directionFix": false, "image": {"tileId": 0, "characterName": "QNEVIESTKA1-neviestka1", "direction": 2, "pattern": 0, "characterIndex": 0}, "list": [{"code": 231, "indent": 0, "parameters": [1, "NPC devka verzia c", 1, 0, 240, 480, 100, 100, 255, 0]}, {"code": 117, "indent": 0, "parameters": [33]}, {"code": 0, "indent": 0, "parameters": []}], "moveFrequency": 3, "moveRoute": {"list": [{"code": 0, "parameters": []}], "repeat": true, "skippable": false, "wait": false}, "moveSpeed": 3, "moveType": 0, "priorityType": 1, "stepAnime": false, "through": false, "trigger": 0, "walkAnime": true}, {"conditions": {"actorId": 1, "actorValid": false, "itemId": 1, "itemValid": false, "selfSwitchCh": "A", "selfSwitchValid": false, "switch1Id": 1, "switch1Valid": false, "switch2Id": 1, "switch2Valid": false, "variableId": 23, "variableValid": true, "variableValue": 7}, "directionFix": false, "image": {"tileId": 0, "characterName": "QNEVIESTKA1-neviestka1", "direction": 2, "pattern": 0, "characterIndex": 0}, "list": [{"code": 231, "indent": 0, "parameters": [1, "NPC devka verzia c", 1, 0, 240, 480, 100, 100, 255, 0]}, {"code": 101, "indent": 0, "parameters": ["", 0, 0, 2]}, {"code": 401, "indent": 0, "parameters": ["Что это за ворота, которые открываются?\\n<Неизвестка>"]}, {"code": 235, "indent": 0, "parameters": [1]}, {"code": 0, "indent": 0, "parameters": []}], "moveFrequency": 3, "moveRoute": {"list": [{"code": 0, "parameters": []}], "repeat": true, "skippable": false, "wait": false}, "moveSpeed": 3, "moveType": 0, "priorityType": 1, "stepAnime": false, "through": false, "trigger": 0, "walkAnime": true}, {"conditions": {"actorId": 1, "actorValid": false, "itemId": 1, "itemValid": false, "selfSwitchCh": "A", "selfSwitchValid": false, "switch1Id": 1, "switch1Valid": false, "switch2Id": 1, "switch2Valid": false, "variableId": 25, "variableValid": true, "variableValue": 1}, "directionFix": false, "image": {"characterIndex": 0, "characterName": "", "direction": 2, "pattern": 0, "tileId": 0}, "list": [{"code": 0, "indent": 0, "parameters": []}], "moveFrequency": 3, "moveRoute": {"list": [{"code": 0, "parameters": []}], "repeat": true, "skippable": false, "wait": false}, "moveSpeed": 3, "moveType": 0, "priorityType": 0, "stepAnime": false, "through": false, "trigger": 0, "walkAnime": true}], "x": 6, "y": 11}, {"id": 6, "name": "bedna", "note": "<collider: Circle, 48, 48, 24, -12>", "pages": [{"conditions": {"actorId": 1, "actorValid": false, "itemId": 1, "itemValid": false, "selfSwitchCh": "A", "selfSwitchValid": false, "switch1Id": 1, "switch1Valid": false, "switch2Id": 1, "switch2Valid": false, "variableId": 1, "variableValid": false, "variableValue": 0}, "directionFix": false, "image": {"characterIndex": 0, "characterName": "", "direction": 2, "pattern": 0, "tileId": 0}, "list": [{"code": 250, "indent": 0, "parameters": [{"name": "Door1", "volume": 90, "pitch": 100, "pan": 0}]}, {"code": 101, "indent": 0, "parameters": ["", 0, 0, 2]}, {"code": 401, "indent": 0, "parameters": ["В бедне не так жарко, как тебе хотелось бы! Медзи"]}, {"code": 401, "indent": 0, "parameters": ["ними[1]альпа[2] ждет тебя."]}, {"code": 126, "indent": 0, "parameters": [4, 0, 0, 1]}, {"code": 123, "indent": 0, "parameters": ["A", 0]}, {"code": 0, "indent": 0, "parameters": []}], "moveFrequency": 3, "moveRoute": {"list": [{"code": 0, "parameters": []}], "repeat": true, "skippable": false, "wait": false}, "moveSpeed": 3, "moveType": 0, "priorityType": 0, "stepAnime": false, "through": false, "trigger": 0, "walkAnime": true}, {"conditions": {"actorId": 1, "actorValid": false, "itemId": 1, "itemValid": false, "selfSwitchCh": "A", "selfSwitchValid": true, "switch1Id": 1, "switch1Valid": false, "switch2Id": 1, "switch2Valid": false, "variableId": 1, "variableValid": false, "variableValue": 0}, "directionFix": false, "image": {"characterIndex": 0, "characterName": "", "direction": 2, "pattern": 0, "tileId": 0}, "list": [{"code": 0, "indent": 0, "parameters": []}], "moveFrequency": 3, "moveRoute": {"list": [{"code": 0, "parameters": []}], "repeat": true, "skippable": false, "wait": false}, "moveSpeed": 3, "moveType": 0, "priorityType": 0, "stepAnime": false, "through": false, "trigger": 0, "walkAnime": true}], "x": 11, "y": 11}, {"id": 7, "name": "sud", "note": "<collider: Circle, 48, 48, 32, 12>", "pages": [{"conditions": {"actorId": 1, "actorValid": false, "itemId": 1, "itemValid": false, "selfSwitchCh": "A", "selfSwitchValid": false, "switch1Id": 1, "switch1Valid": false, "switch2Id": 1, "switch2Valid": false, "variableId": 1, "variableValid": false, "variableValue": 0}, "directionFix": false, "image": {"characterIndex": 0, "characterName": "", "direction": 2, "pattern": 0, "tileId": 0}, "list": [{"code": 250, "indent": 0, "parameters": [{"name": "Door1", "volume": 90, "pitch": 100, "pan": 0}]}, {"code": 101, "indent": 0, "parameters": ["", 0, 0, 2]}, {"code": 401, "indent": 0, "parameters": ["В будущем медзи кадеяким харабурдим[1] каша[2] будет скрыта."]}, {"code": 126, "indent": 0, "parameters": [19, 0, 0, 1]}, {"code": 123, "indent": 0, "parameters": ["A", 0]}, {"code": 0, "indent": 0, "parameters": []}], "moveFrequency": 3, "moveRoute": {"list": [{"code": 0, "parameters": []}], "repeat": true, "skippable": false, "wait": false}, "moveSpeed": 3, "moveType": 0, "priorityType": 0, "stepAnime": false, "through": false, "trigger": 0, "walkAnime": true}, {"conditions": {"actorId": 1, "actorValid": false, "itemId": 1, "itemValid": false, "selfSwitchCh": "A", "selfSwitchValid": true, "switch1Id": 1, "switch1Valid": false, "switch2Id": 1, "switch2Valid": false, "variableId": 1, "variableValid": false, "variableValue": 0}, "directionFix": false, "image": {"characterIndex": 0, "characterName": "", "direction": 2, "pattern": 0, "tileId": 0}, "list": [{"code": 0, "indent": 0, "parameters": []}], "moveFrequency": 3, "moveRoute": {"list": [{"code": 0, "parameters": []}], "repeat": true, "skippable": false, "wait": false}, "moveSpeed": 3, "moveType": 0, "priorityType": 0, "stepAnime": false, "through": false, "trigger": 0, "walkAnime": true}], "x": 12, "y": 10}, {"id": 8, "name": "EV008", "note": "<collider: Circle, 120, 120, 0, 24>", "pages": [{"conditions": {"actorId": 1, "actorValid": false, "itemId": 1, "itemValid": false, "selfSwitchCh": "A", "selfSwitchValid": false, "switch1Id": 1, "switch1Valid": false, "switch2Id": 1, "switch2Valid": false, "variableId": 1, "variableValid": false, "variableValue": 0}, "directionFix": false, "image": {"characterIndex": 0, "characterName": "", "direction": 2, "pattern": 0, "tileId": 0}, "list": [{"code": 111, "indent": 0, "parameters": [4, 2, 0]}, {"code": 231, "indent": 1, "parameters": [1, "hrdina palo", 1, 0, 760, 540, 100, 100, 255, 0]}, {"code": 101, "indent": 1, "parameters": ["", 0, 0, 2]}, {"code": 401, "indent": 1, "parameters": ["Примем? \\n<Павел>"]}, {"code": 235, "indent": 1, "parameters": [1]}, {"code": 231, "indent": 1, "parameters": [1, "hrdina matej", 1, 0, 220, 550, 100, 100, 255, 0]}, {"code": 101, "indent": 1, "parameters": ["", 0, 0, 2]}, {"code": 401, "indent": 1, "parameters": ["В невестинки? Так же, как и в другом месте! \\n<Матей>"]}, {"code": 235, "indent": 1, "parameters": [1]}, {"code": 0, "indent": 1, "parameters": []}, {"code": 411, "indent": 0, "parameters": []}, {"code": 111, "indent": 1, "parameters": [2, "A", 0]}, {"code": 221, "indent": 2, "parameters": []}, {"code": 222, "indent": 2, "parameters": []}, {"code": 314, "indent": 2, "parameters": [0, 0]}, {"code": 101, "indent": 2, "parameters": ["", 0, 0, 2]}, {"code": 401, "indent": 2, "parameters": ["Я хочу, чтобы ты задремал. Лепше с тобой, но ты зашел ко мне."]}, {"code": 0, "indent": 2, "parameters": []}, {"code": 411, "indent": 1, "parameters": []}, {"code": 231, "indent": 2, "parameters": [1, "hrdina palo", 1, 0, 760, 540, 100, 100, 255, 0]}, {"code": 101, "indent": 2, "parameters": ["", 0, 0, 2]}, {"code": 401, "indent": 2, "parameters": ["Примем? \\n<Павел>"]}, {"code": 101, "indent": 2, "parameters": ["", 0, 0, 2]}, {"code": 401, "indent": 2, "parameters": ["<Вордворп>Яж, я хочу, чтобы Матей остался при земепанови. Я"]}, {"code": 401, "indent": 2, "parameters": ["ждал, я ждал тебя.\\к[1]<Павел>"]}, {"code": 235, "indent": 2, "parameters": [1]}, {"code": 221, "indent": 2, "parameters": []}, {"code": 222, "indent": 2, "parameters": []}, {"code": 314, "indent": 2, "parameters": [0, 0]}, {"code": 101, "indent": 2, "parameters": ["", 0, 0, 2]}, {"code": 401, "indent": 2, "parameters": ["Я хочу, чтобы ты задремал. Лепше с тобой, но ты зашел ко мне."]}, {"code": 0, "indent": 2, "parameters": []}, {"code": 412, "indent": 1, "parameters": []}, {"code": 0, "indent": 1, "parameters": []}, {"code": 412, "indent": 0, "parameters": []}, {"code": 0, "indent": 0, "parameters": []}], "moveFrequency": 3, "moveRoute": {"list": [{"code": 0, "parameters": []}], "repeat": true, "skippable": false, "wait": false}, "moveSpeed": 3, "moveType": 0, "priorityType": 1, "stepAnime": false, "through": false, "trigger": 1, "walkAnime": true}, {"conditions": {"actorId": 1, "actorValid": false, "itemId": 1, "itemValid": false, "selfSwitchCh": "A", "selfSwitchValid": false, "switch1Id": 1, "switch1Valid": false, "switch2Id": 1, "switch2Valid": false, "variableId": 25, "variableValid": true, "variableValue": 1}, "directionFix": false, "image": {"characterIndex": 0, "characterName": "", "direction": 2, "pattern": 0, "tileId": 0}, "list": [{"code": 231, "indent": 0, "parameters": [1, "hrdina palo", 1, 0, 760, 540, 100, 100, 255, 0]}, {"code": 101, "indent": 0, "parameters": ["", 0, 0, 2]}, {"code": 401, "indent": 0, "parameters": ["Чудесная девочка. Сна, которой я никогда не был. \\n<Павел>"]}, {"code": 235, "indent": 0, "parameters": [1]}, {"code": 0, "indent": 0, "parameters": []}], "moveFrequency": 3, "moveRoute": {"list": [{"code": 0, "parameters": []}], "repeat": true, "skippable": false, "wait": false}, "moveSpeed": 3, "moveType": 0, "priorityType": 1, "stepAnime": false, "through": false, "trigger": 1, "walkAnime": true}], "x": 14, "y": 6}, {"id": 9, "name": "EV009", "note": "", "pages": [{"conditions": {"actorId": 1, "actorValid": false, "itemId": 1, "itemValid": false, "selfSwitchCh": "A", "selfSwitchValid": false, "switch1Id": 1, "switch1Valid": false, "switch2Id": 1, "switch2Valid": false, "variableId": 23, "variableValid": true, "variableValue": 9}, "directionFix": false, "image": {"tileId": 0, "characterName": "QDZIVCE-dzivce", "direction": 2, "pattern": 0, "characterIndex": 0}, "list": [{"code": 0, "indent": 0, "parameters": []}], "moveFrequency": 3, "moveRoute": {"list": [{"code": 0, "parameters": []}], "repeat": true, "skippable": false, "wait": false}, "moveSpeed": 3, "moveType": 0, "priorityType": 1, "stepAnime": false, "through": false, "trigger": 0, "walkAnime": true}, {"conditions": {"actorId": 1, "actorValid": false, "itemId": 1, "itemValid": false, "selfSwitchCh": "A", "selfSwitchValid": false, "switch1Id": 1, "switch1Valid": false, "switch2Id": 1, "switch2Valid": false, "variableId": 25, "variableValid": true, "variableValue": 1}, "directionFix": false, "image": {"characterIndex": 0, "characterName": "", "direction": 2, "pattern": 0, "tileId": 0}, "list": [{"code": 0, "indent": 0, "parameters": []}], "moveFrequency": 3, "moveRoute": {"list": [{"code": 0, "parameters": []}], "repeat": true, "skippable": false, "wait": false}, "moveSpeed": 3, "moveType": 0, "priorityType": 0, "stepAnime": false, "through": false, "trigger": 0, "walkAnime": true}], "x": 7, "y": 10}]}